{
	"submit": "Ingresar",
	"office": "Oficina",
	"employeeFormTitle": "Ingreso de Colaboradores",
	"welcomeHome": "¡Bienvenido a la aplicación de registro de visitantes!",
	"welcomeHomeAdmin": "¡Bienvenido al modulo de administrador!",
	"officePlaceHolder": "Selecciona el pais de destino:",
	"documentPlaceHolder": "Numero de documento",
	"namePlaceHolder": "Nombre",
	"emergencyContactPlaceHolder": "Numero de contacto de emergencia",
	"epsPlaceHolder": "Empresa prestadora de salud",
	"arlPlaceHolder": "Empresa prestadora de salud Laboral",
	"rhPlaceHolder": "RH",
	"visitingNamePlaceHolder": "Funcionario a quien visita",
	"entryDatePlaceHolder": "Fecha de ingreso",
	"exitDatePlaceHolder": "Fecha y hora de salida",
	"employeeFormButton": "Ingreso de colaboradores",
	"visitorFormButton": "Ingreso de visitantes",
	"transportFormButton": "Ingreso de transportes",
	"dataTreatment": "He leido y acepto los terminos y condiciones, para leer los terminos y condiciones haga",
	"visitorFormTitle": "Ingreso de Visitantes",
	"clickTermsConditions": "click aqui",
	"cartaPorte": "Carta de porte",
	"numTrailer": "Numero de trailer",
	"entryTransport": "Ingreso de transportes",
	"lastNamePlaceHolder": "Apellido",
	"phone": "Telefono",
	"transportCompany": "EmpresaTransportadora",
	"netWeight": "Peso neto en KG",
	"entryNetWeight": "Peso de ingreso en KG",
	"exitNetWeight": "Peso de salida en KG",
	"plate": "Placa",
	"trailerNumber": "Numero de trailer",
	"origin": "Origen",
	"Destination": "Destino",
	"Precintos": "Precintos",
	"imgWeight": "Imagen de peso en bascula",
	"observation": "Observaciones",
	"adminButton": "Inicia Sesión",
	"username": "Usuario",
	"password": "Contraseña",
	"loginMessage": "Inicia Sesión",
	"Logout": "Cerrar Sesión",
	"AdminOffice": "Pais de destino",
	"DownloadImage": "Descargar imagen",
	"Update": "Actualizar",
	"BackHome":"Volver al inicio",
	"exitFormat":"Formato de salida o permiso temporal",
	"tipoPermiso":"Tipo de permiso",
	"clickTermsConditions2":"click aqui",
	"areYouCaravelaClient":"¿Eres un cliente de Caravela?","expeditionDatePlaceholder":"Fecha de expedición de documento",
	"daysInOfficePlaceholder":"¿Cuantos dias estarás en la oficina?",
	"contractorNamePlaceholder":"Empresa o contratista",
	"loadingText":"Cargando",
	"visitReasonPlaceholder":"Motivo de la visita",
	"fieldRequired":"Este campo es obligatorio",
	"registrationSuccess":"Registro exitoso"

}
